README.rst
setup.py
kuvalda/__init__.py
kuvalda/kuvalda.py
kuvalda.egg-info/PKG-INFO
kuvalda.egg-info/SOURCES.txt
kuvalda.egg-info/dependency_links.txt
kuvalda.egg-info/top_level.txt