Metadata-Version: 1.1
Name: kuvalda
Version: 0.1.0
Summary: Damn Simple Validation Kit.
Home-page: https://github.com/little-arhat/kuvalda
Author: Roma Sokolov
Author-email: sokolov.r.v@gmail.com
License: MIT
Platform: UNKNOWN
Classifier: Natural Language :: English
Classifier: License :: OSI Approved :: MIT License
Classifier: Programming Language :: Python
Classifier: Programming Language :: Python :: 2.6
Classifier: Programming Language :: Python :: 2.7
Classifier: Programming Language :: Python :: 3
